gravixlayer/__init__.py
gravixlayer/client.py
gravixlayer/resources/__init__.py
gravixlayer/resources/chat/__init__.py
gravixlayer/resources/chat/completions.py
gravixlayer/types/__init__.py
gravixlayer/types/chat.py
gravixlayer-0.1.11.dist-info/licenses/LICENSE
gravixlayer-0.1.11.dist-info/METADATA
gravixlayer-0.1.11.dist-info/WHEEL
gravixlayer-0.1.11.dist-info/top_level.txt
gravixlayer-0.1.11.dist-info/RECORD
